{"title":"레고 추천 톱 10","description":"레고 정보가 궁금하신가요? 종류가 너무 많아서 도대체 어떤 제품을 구매해야할지 고민이시죠?\n실시간 통계를 바탕으로 사용자들에게 많은 사랑을 받고 있는 제품들을 소개해드립니다.\n추천드린 제품들을 꼼꼼히 비교해보시고 합리적인 소비하시길 바랍니다!","date":"2022-02-22 00:00:03","category":"","products":[{"productId":4776873709,"productName":"레고 시티 60283 휴가용 캠핑밴, 1개, 혼합색상","productPrice":26970,"productImage":"https://static.coupangcdn.com/image/retail/images/1211302031623729-b213c47f-79a7-4d54-9611-5fe7db51f389.jpg","productUrl":"https://link.coupang.com/re/AFFSDP?lptag=AF7122381&pageKey=4776873709&itemId=6103971454&vendorItemId=73400334121&traceid=V0-153-06cc62c3619dd3b0","keyword":"레고","rank":1,"isRocket":true,"isFreeShipping":false},{"productId":5583930054,"productName":"레고 크리에이터 엑스퍼트 10280 꽃다발","productPrice":58200,"productImage":"https://static.coupangcdn.com/image/retail/images/1211297021487222-2361cf36-2017-4847-80a9-2ab2b7d410d3.jpg","productUrl":"https://link.coupang.com/re/AFFSDP?lptag=AF7122381&pageKey=5583930054&itemId=8934428619&vendorItemId=73294972682&traceid=V0-153-5cc77f8261f57ee2","keyword":"레고","rank":2,"isRocket":true,"isFreeShipping":false},{"productId":4919368195,"productName":"레고 테크닉 42117 경주용 비행기","productPrice":23180,"productImage":"https://static.coupangcdn.com/image/retail/images/1211300253345964-ddd4050f-4359-4d8c-a97b-b0ba2363ef3c.jpg","productUrl":"https://link.coupang.com/re/AFFSDP?lptag=AF7122381&pageKey=4919368195&itemId=6443640920&vendorItemId=73400334057&traceid=V0-153-30792178746dff97","keyword":"레고","rank":3,"isRocket":true,"isFreeShipping":false},{"productId":4906020162,"productName":"레고 테크닉 42123 맥라렌 세나 GTR, 혼합색상","productPrice":73090,"productImage":"https://static.coupangcdn.com/image/retail/images/1211300591492395-91d189d7-4206-4a63-b9f7-5417d135f297.jpg","productUrl":"https://link.coupang.com/re/AFFSDP?lptag=AF7122381&pageKey=4906020162&itemId=6401964885&vendorItemId=73400332756&traceid=V0-153-3a549b91c5e27ad3","keyword":"레고","rank":4,"isRocket":true,"isFreeShipping":false},{"productId":4776874944,"productName":"레고 테크닉 42122 지프 랭글러, 혼합색상","productPrice":67490,"productImage":"https://static.coupangcdn.com/image/retail/images/1211300490053908-f861a9d1-1ad1-41c7-8488-3b162c596953.jpg","productUrl":"https://link.coupang.com/re/AFFSDP?lptag=AF7122381&pageKey=4776874944&itemId=6103974031&vendorItemId=73400337041&traceid=V0-153-f20d72c5acbc186e","keyword":"레고","rank":5,"isRocket":true,"isFreeShipping":false},{"productId":1139170197,"productName":"레고 닌자고 정글 레이더 71700, 혼합 색상","productPrice":37900,"productImage":"https://static.coupangcdn.com/image/vendor_inventory/1a9e/3bca87db0d899aba32850257775571068ef7f0d0ba5104aac1f2751bd3f8.jpg","productUrl":"https://link.coupang.com/re/AFFSDP?lptag=AF7122381&pageKey=1139170197&itemId=2109819633&vendorItemId=73357949190&traceid=V0-153-a761a444898d8d43","keyword":"레고","rank":6,"isRocket":false,"isFreeShipping":true},{"productId":1139069160,"productName":"레고 크리에이터 스포츠카 31100, 혼합 색상","productPrice":12400,"productImage":"https://static.coupangcdn.com/image/retail/images/2020/01/02/11/8/08c59e0c-1af2-45bf-83de-8831225f7ba9.jpg","productUrl":"https://link.coupang.com/re/AFFSDP?lptag=AF7122381&pageKey=1139069160&itemId=2109722724&vendorItemId=70108474228&traceid=V0-153-12a0a5391c86eead","keyword":"레고","rank":7,"isRocket":true,"isFreeShipping":false},{"productId":4733942445,"productName":"레고 닌자고 71738 레거시 쟌의 타이탄 로봇 전투, 혼합색상","productPrice":73000,"productImage":"https://static.coupangcdn.com/image/retail/images/1213588351178489-b2ed32a6-76ec-445e-b59e-e34ae43830fa.jpg","productUrl":"https://link.coupang.com/re/AFFSDP?lptag=AF7122381&pageKey=4733942445&itemId=6004553372&vendorItemId=73400336806&traceid=V0-153-2f34b3b8544c4908","keyword":"레고","rank":8,"isRocket":true,"isFreeShipping":false},{"productId":6239544136,"productName":"레고 닌자고 닌자 울트라 콤보 로봇 71765, 혼합색상","productPrice":111900,"productImage":"https://static.coupangcdn.com/image/rs_quotation_api/hekzhfur/565ac979c9a043778e76a6fa0306546f.jpg","productUrl":"https://link.coupang.com/re/AFFSDP?lptag=AF7122381&pageKey=6239544136&itemId=12586453865&vendorItemId=79854425948&traceid=V0-153-ce90ca3a423a553e","keyword":"레고","rank":9,"isRocket":true,"isFreeShipping":false},{"productId":4797048774,"productName":"LM나무공방LM 레고호환블럭 건축","productPrice":3690,"productImage":"https://static.coupangcdn.com/image/retail/images/2021/07/08/14/3/2c28f7dd-f5b8-4bb9-a405-da3ff73a0ca5.jpg","productUrl":"https://link.coupang.com/re/AFFSDP?lptag=AF7122381&pageKey=4797048774&itemId=6153775155&vendorItemId=77269200789&traceid=V0-153-00951f2ad119e3b8","keyword":"레고","rank":10,"isRocket":true,"isFreeShipping":false}],"keyword":"레고"}