{"title":"아디다스골프화 추천 순위 Top 10","description":"최근 들어 아디다스골프화 순위를 검색하시는 분들이 많습니다.\n검색어 추이를 분석하다보면 현재 많은 분들이 어떤 제품에 관심이 많은지 조금이나마 유추할 수 있는데요,\n이러한 데이터를 기반으로 해당 카테고리에서 수많은 분들이 구매하셨고 리뷰를 남겨주신, 선택하셔도 후회 없을만한 제품들을 소개해드리고자 합니다.\n목록에서 여러가지 제품들을 직접 살펴보시고 리뷰도 읽어보시고 결정하세요:)","date":"2022-03-08 22:30:03","category":"","products":[{"productId":4833297431,"productName":"아디다스 남성용 EQT 보아 Boost 골프화 FX6639","productPrice":149000,"productImage":"https://static.coupangcdn.com/image/retail/images/2021/02/22/17/7/fc3de605-914b-4cb4-81d2-020da52ea89a.jpg","productUrl":"https://link.coupang.com/re/AFFSDP?lptag=AF7122381&pageKey=4833297431&itemId=6239515977&vendorItemId=74102513388&traceid=V0-153-0b3f2f98f775ac79","keyword":"아디다스골프화","rank":1,"isRocket":true,"isFreeShipping":false},{"productId":5972120623,"productName":"[아디다스골프] 21년 신제품 알파플렉스21 보아 남성 스파이크 골프화","productPrice":221660,"productImage":"https://static.coupangcdn.com/image/vendor_inventory/183b/facf1da398eb30a6f7b598ff0dd1932f14bac642cf6ea85a9450c85cfa69.jpg","productUrl":"https://link.coupang.com/re/AFFSDP?lptag=AF7122381&pageKey=5972120623&itemId=10729972802&vendorItemId=79316512291&traceid=V0-153-f1ac8066d6268900","keyword":"아디다스골프화","rank":2,"isRocket":false,"isFreeShipping":false},{"productId":6148874449,"productName":"아놀드파마 가죽 골프화 패션 골프 스니커즈 운동화 스크린 연습용 클래식 실내 신발 발편한 독일군 명품 경량 남성 여성","productPrice":51800,"productImage":"https://static.coupangcdn.com/image/vendor_inventory/5f40/c4fd50a43f642c32b36d14c731813f1e19cdb8716ea1d7918d4f0a13a681.jpg","productUrl":"https://link.coupang.com/re/AFFSDP?lptag=AF7122381&pageKey=6148874449&itemId=11854063154&vendorItemId=79127262348&traceid=V0-153-4a4ce957286219d5","keyword":"아디다스골프화","rank":3,"isRocket":false,"isFreeShipping":true},{"productId":5872610126,"productName":"아놀드파마 보아 다이얼 수제 골프 구두 골프화 명품 스니커즈 키높이 운동화 남성 스파이크리스 필드","productPrice":49800,"productImage":"https://static.coupangcdn.com/image/vendor_inventory/2381/cea2be31be6d2b50bb3769704e67ae4aa7ef6f89594f706610b5234ff7a3.jpg","productUrl":"https://link.coupang.com/re/AFFSDP?lptag=AF7122381&pageKey=5872610126&itemId=10278887066&vendorItemId=77561253695&traceid=V0-153-c1fb98d47bb54c2c","keyword":"아디다스골프화","rank":4,"isRocket":false,"isFreeShipping":true},{"productId":6377413840,"productName":"수제 여성 골프화 2컬러","productPrice":159000,"productImage":"https://static.coupangcdn.com/image/vendor_inventory/f39b/6ea2e6770a4ed4a7395ba893dd9ae2b4210a216d0610614300c1fc91217f.jpeg","productUrl":"https://link.coupang.com/re/AFFSDP?lptag=AF7122381&pageKey=6377413840&itemId=13533975084&vendorItemId=80787743009&traceid=V0-153-59ea3be9f2ceb527","keyword":"아디다스골프화","rank":5,"isRocket":false,"isFreeShipping":true},{"productId":4682947041,"productName":"아디다스골프 아디다스 코어 퍼포먼스 보아 남성골프화","productPrice":217200,"productImage":"https://static.coupangcdn.com/image/vendor_inventory/d9fa/5375d4eff944db7d0cf9841799bb2a74d1a5035bc3db2e837828895b08a7.jpg","productUrl":"https://link.coupang.com/re/AFFSDP?lptag=AF7122381&pageKey=4682947041&itemId=5874721816&vendorItemId=80208097156&traceid=V0-153-205ab63790ac6960","keyword":"아디다스골프화","rank":6,"isRocket":false,"isFreeShipping":true},{"productId":6321545740,"productName":"[아디다스코리아정품] 22년 코드케이오스 레이스 골프화 GW53415995","productPrice":170000,"productImage":"https://static.coupangcdn.com/image/vendor_inventory/4690/7cb072f25051e7319ba357ef7760bde718fe6f6306d5305a61a94af3dc18.jpg","productUrl":"https://link.coupang.com/re/AFFSDP?lptag=AF7122381&pageKey=6321545740&itemId=13177793700&vendorItemId=80436286314&traceid=V0-153-cf4d8511406bccb1","keyword":"아디다스골프화","rank":7,"isRocket":false,"isFreeShipping":true},{"productId":6334818513,"productName":"아놀드파마 국산 골프 구두 남자 수제 골프화 키높이 스니커즈 남성 캐주얼 명품 패션 스파이크 실내 남성","productPrice":37800,"productImage":"https://static.coupangcdn.com/image/vendor_inventory/fbcf/44dfbf75e10151af8830097eb3431785e1dffeeffef5555961387904db83.jpeg","productUrl":"https://link.coupang.com/re/AFFSDP?lptag=AF7122381&pageKey=6334818513&itemId=13262916881&vendorItemId=77559959227&traceid=V0-153-a7c1232a1e72d747","keyword":"아디다스골프화","rank":8,"isRocket":false,"isFreeShipping":true},{"productId":5239575165,"productName":"아디다스골프 아디다스골프 여성용 골프화 EG6485 우먼스 투어360 XT-SL","productPrice":125400,"productImage":"https://static.coupangcdn.com/image/vendor_inventory/5b48/0c5ba259b5bdc5e5b64be170962f5222f10209de21a0ad6745551f65e735.jpg","productUrl":"https://link.coupang.com/re/AFFSDP?lptag=AF7122381&pageKey=5239575165&itemId=7396642485&vendorItemId=79512499495&traceid=V0-153-342397090e907ab0","keyword":"아디다스골프화","rank":9,"isRocket":false,"isFreeShipping":true},{"productId":6346914373,"productName":"아놀드파마 명품 수제 가죽 골프화 보아 다이얼 골프 스니커즈 운동화 클래식 캐주얼 신발 푹신한 편안한","productPrice":57500,"productImage":"https://static.coupangcdn.com/image/vendor_inventory/6382/f9fffaa84950c64e4ea510fa809ade3dcedf31f96bcd51e639b13c3737da.jpg","productUrl":"https://link.coupang.com/re/AFFSDP?lptag=AF7122381&pageKey=6346914373&itemId=13339465790&vendorItemId=80594707926&traceid=V0-153-b324802e9108193c","keyword":"아디다스골프화","rank":10,"isRocket":false,"isFreeShipping":true}],"keyword":"아디다스골프화"}